tqdm_publisher/__init__.py
tqdm_publisher/_handler.py
tqdm_publisher/_publisher.py
tqdm_publisher/_subscriber.py
tqdm_publisher/testing.py
tqdm_publisher/_demos/__init__.py
tqdm_publisher/_demos/_client.css
tqdm_publisher/_demos/_demo_command_line_interface.py
tqdm_publisher/_demos/_multiple_bars/README.md
tqdm_publisher/_demos/_multiple_bars/_client.html
tqdm_publisher/_demos/_multiple_bars/_client.js
tqdm_publisher/_demos/_multiple_bars/_server.py
tqdm_publisher/_demos/_parallel_bars/README.md
tqdm_publisher/_demos/_parallel_bars/_client.html
tqdm_publisher/_demos/_parallel_bars/_client.js
tqdm_publisher/_demos/_parallel_bars/_server.py
tqdm_publisher/_demos/_single_bar/README.md
tqdm_publisher/_demos/_single_bar/_client.html
tqdm_publisher/_demos/_single_bar/_client.js
tqdm_publisher/_demos/_single_bar/_server.py
tqdm_publisher/_demos/utils/EventSourceManager.js
tqdm_publisher/_demos/utils/WebSocketManager.js
tqdm_publisher/_demos/utils/elements.js
tqdm_publisher-0.1.1.dist-info/METADATA
tqdm_publisher-0.1.1.dist-info/WHEEL
tqdm_publisher-0.1.1.dist-info/entry_points.txt
tqdm_publisher-0.1.1.dist-info/RECORD
