Metadata-Version: 2.3
Name: tqdm_publisher
Version: 0.1.1
Summary: Extends the base tqdm progress bar with a subscribe method that can expose updates to external (potentially non-Python) processes.
Project-URL: Homepage, https://github.com/catalystneuro/tqdm_publisher
Project-URL: Bug Tracker, https://github.com/catalystneuro/tqdm_publisher/issues
Author-email: Garrett Flynn <garrett.flynn@catalystneuro.com>, Cody Baker <cody.baker@catalystneuro.com>
License: BSD 3-Clause License
Keywords: bar,meter,progress,progressbar,progressmeter,publish-subscribe pattern,pubsub,time,tqdm
Classifier: Intended Audience :: Developers
Classifier: License :: OSI Approved :: BSD License
Classifier: Operating System :: MacOS
Classifier: Operating System :: Microsoft :: Windows
Classifier: Operating System :: Unix
Classifier: Programming Language :: Python
Classifier: Programming Language :: Python :: 3.8
Classifier: Programming Language :: Python :: 3.9
Classifier: Programming Language :: Python :: 3.10
Classifier: Programming Language :: Python :: 3.11
Requires-Python: >=3.9
Requires-Dist: tqdm>=4.49.0
Provides-Extra: demo
Requires-Dist: flask; extra == 'demo'
Requires-Dist: flask-cors; extra == 'demo'
Requires-Dist: requests; extra == 'demo'
Requires-Dist: websockets; extra == 'demo'
Provides-Extra: test
Requires-Dist: pytest; extra == 'test'
Requires-Dist: pytest-asyncio; extra == 'test'
Requires-Dist: pytest-cov; extra == 'test'
